AM2940/donegen.sv
module done_gen(dowc, dowr, doac, cinw, mode, done);
  input[7:0] dowc, dowr, doac;
  input[1:0] mode;
  input cinw;
  output reg done;
  
  always @(dowc or dowr or doac or cinw or mode)
    casex({mode, cinw})
      3'b00_0: done = (dowc === 8'b1);
      3'b00_1: done = ~(dowc);
      3'b01_0: done = (dowc + 1 === dowr);
      3'b01_1: done = (dowc === dowr);
      3'b10_x: done = (dowc === doac);
      3'b11_x: done = 1'b0;
    endcase
endmodule

AM2940/multiplexer.sv
module mux_1_2(din0, din1, dout, sel);
  
  input [7:0] din0, din1;
  input sel;
  output [7:0] dout;
  
  assign dout = sel ? din1 : din0;
endmodule

module mux_1_3(din0, din1, din2, dout, sel);
  
  input [7:0] din0, din1;
  input [2:0] din2;
  output reg [7:0] dout;
  input [1:0] sel;
  always @(din0 or din1 or din2 or sel)
    casex(sel)
      3'b00: dout = din0;
      3'b01: dout = din1;
      3'b1x: dout = {5'b11111,din2};
    endcase
  
endmodule

AM2940/register.sv
module reg8(clk, pl, din, dout);
  
  input clk, pl;
  input[7:0] din;
  output reg[7:0] dout;
  
  always @(posedge clk)
      if(pl)
        dout <= din;


endmodule

module reg3(clk, pl, din, dout);
  
  input clk, pl;
  input[2:0] din;
  output reg[2:0] dout;
  
  always @(posedge clk)
      if(pl)
        dout <= din;
  
endmodule

AM2940/counter.sv
module counter_8b(clk, reset, pl, ci, cout, dec, inc, encnt, di, dout);
  input clk, reset, encnt, ci, inc, dec, pl;
  input [7:0] di;
  output reg[7:0] dout;
  output cout;
    
  assign cout = !((!((dout === 8'hff)&& encnt && inc && (!ci))) && (!((dout === 8'h0) && encnt && dec && (!ci))));
  
  always @(posedge clk)
    if(reset)
      dout <= 8'b0;
  	else
      if(pl)
        dout <= di;
      else
        if(encnt && !ci)
          casex({inc, dec})
            2'b1_x: dout <= dout + 1;
            2'b0_1: dout <= dout - 1;
          endcase
  
endmodule

AM2940/instructiondec.sv
module instruction_decoder(I, CR, plar, plwr, sela, selw, plcr,
                           seld, plac, ena, inca, deca, resw,
                           plwc, enw, incw, decw, oedata);
  input [2:0] I, CR;
  output reg plar, plwr, sela, selw, plcr, plac, ena, inca, deca, resw, plwc, enw, incw, decw, oedata;
  output reg [1:0] seld;
  
    always@(I or CR)
    casex({I,CR})
      6'b000_xxx: begin
        plar = 1'b0;
        plwr = 1'b0;
        sela = 1'bx;
        selw = 1'bx;
        plcr = 1'b1;
        seld = 2'bxx;
        plac = 1'b0;
        ena = 1'b0;
        inca = 1'b0;
        deca = 1'b0;
        resw = 1'b0;
        plwc = 1'b0;
        enw = 1'b0;
        incw = 1'b0;
        decw = 1'b0;
        oedata = 1'b0;
      end
      
      6'b001_xxx: begin
        plar = 1'b0;
        plwr = 1'b0;
        sela = 1'bx;
        selw = 1'bx;
        plcr = 1'b0;
        seld = 2'b1x;
        plac = 1'b0;
        ena = 1'b0;
        inca = 1'b0;
        deca = 1'b0;
        resw = 1'b0;
        plwc = 1'b0;
        enw = 1'b0;
        incw = 1'b0;
        decw = 1'b0;
        oedata = 1'b1;
      end
      
      6'b010_xxx: begin
        plar = 1'b0;
        plwr = 1'b0;
        sela = 1'bx;
        selw = 1'bx;
        plcr = 1'b0;
        seld = 2'b01;
        plac = 1'b0;
        ena = 1'b0;
        inca = 1'b0;
        deca = 1'b0;
        resw = 1'b0;
        plwc = 1'b0;
        enw = 1'b0;
        incw = 1'b0;
        decw = 1'b0;
        oedata = 1'b1;
      end
      6'b011_xxx: begin
        plar = 1'b0;
        plwr = 1'b0;
        sela = 1'bx;
        selw = 1'bx;
        plcr = 1'b0;
        seld = 2'b00;
        plac = 1'b0;
        ena = 1'b0;
        inca = 1'b0;
        deca = 1'b0;
        resw = 1'b0;
        plwc = 1'b0;
        enw = 1'b0;
        incw = 1'b0;
        decw = 1'b0;
        oedata = 1'b1;
      end
      
      6'b100_xx0, 6'b100_x11: begin
        plar = 1'b0;
        plwr = 1'b0;
        sela = 1'b1;
        selw = 1'b1;
        plcr = 1'b0;
        seld = 2'bxx;
        plac = 1'b1;
        ena = 1'b0;
        inca = 1'b0;
        deca = 1'b0;
        resw = 1'b0;
        plwc = 1'b0;
        enw = 1'b0;
        incw = 1'b0;
        decw = 1'b0;
        oedata = 1'b0;
      end
      
      6'b100_x01: begin
        plar = 1'b0;
        plwr = 1'b0;
        sela = 1'b1;
        selw = 1'bx;
        plcr = 1'b0;
        seld = 2'bxx;
        plac = 1'b1;
        ena = 1'b0;
        inca = 1'b0;
        deca = 1'b0;
        resw = 1'b1;
        plwc = 1'b0;
        enw = 1'b0;
        incw = 1'b0;
        decw = 1'b0;
        oedata = 1'b0;
      end
      
      6'b101_xxx: begin
        plar = 1'b1;
        plwr = 1'b0;
        sela = 1'b0;
        selw = 1'bx;
        plcr = 1'b0;
        seld = 2'bxx;
        plac = 1'b1;
        ena = 1'b0;
        inca = 1'b0;
        deca = 1'b0;
        resw = 1'b0;
        plwc = 1'b0;
        enw = 1'b0;
        incw = 1'b0;
        decw = 1'b0;
        oedata = 1'b0;
      end
     6'b110_xx0, 6'b110_x11: begin
        plar = 1'b0;
        plwr = 1'b1;
        sela = 1'bx;
        selw = 1'b0;
        plcr = 1'b0;
        seld = 2'bxx;
        plac = 1'b0;
        ena = 1'b0;
        inca = 1'b0;
        deca = 1'b0;
        resw = 1'b0;
        plwc = 1'b1;
        enw = 1'b0;
        incw = 1'b0;
        decw = 1'b0;
        oedata = 1'b0;
      end
      
      6'b110_x01: begin
        plar = 1'b0;
        plwr = 1'b1;
        sela = 1'bx;
        selw = 1'bx;
        plcr = 1'b0;
        seld = 2'bxx;
        plac = 1'b0;
        ena = 1'b0;
        inca = 1'b0;
        deca = 1'b0;
        resw = 1'b1;
        plwc = 1'b0;
        enw = 1'b0;
        incw = 1'b0;
        decw = 1'b0;
        oedata = 1'b0;
      end
      
      6'b111_000: begin
        plar = 1'b0;
        plwr = 1'b0;
        sela = 1'bx;
        selw = 1'bx;
        plcr = 1'b0;
        seld = 2'bxx;
        plac = 1'b0;
        ena = 1'b1;
        inca = 1'b1;
        deca = 1'b0;
        resw = 1'b0;
        plwc = 1'b0;
        enw = 1'b1;
        incw = 1'b0;
        decw = 1'b1;
        oedata = 1'b0;
      end
      
      6'b111_0x1: begin
        plar = 1'b0;
        plwr = 1'b0;
        sela = 1'bx;
        selw = 1'bx;
        plcr = 1'b0;
        seld = 2'bxx;
        plac = 1'b0;
        ena = 1'b1;
        inca = 1'b1;
        deca = 1'b0;
        resw = 1'b0;
        plwc = 1'b0;
        enw = 1'b1;
        incw = 1'b1;
        decw = 1'b0;
        oedata = 1'b0;
      end
      
      6'b111_010: begin
        plar = 1'b0;
        plwr = 1'b0;
        sela = 1'bx;
        selw = 1'bx;
        plcr = 1'b0;
        seld = 2'bxx;
        plac = 1'b0;
        ena = 1'b1;
        inca = 1'b1;
        deca = 1'b0;
        resw = 1'b0;
        plwc = 1'b0;
        enw = 1'b0;
        incw = 1'b0;
        decw = 1'b0;
        oedata = 1'b0;
      end
      
      6'b111_100: begin
        plar = 1'b0;
        plwr = 1'b0;
        sela = 1'bx;
        selw = 1'bx;
        plcr = 1'b0;
        seld = 2'bxx;
        plac = 1'b0;
        ena = 1'b1;
        inca = 1'b0;
        deca = 1'b1;
        resw = 1'b0;
        plwc = 1'b0;
        enw = 1'b1;
        incw = 1'b0;
        decw = 1'b1;
        oedata = 1'b0;
      end
      
      6'b111_1x1: begin
        plar = 1'b0;
        plwr = 1'b0;
        sela = 1'bx;
        selw = 1'bx;
        plcr = 1'b0;
        seld = 2'bxx;
        plac = 1'b0;
        ena = 1'b1;
        inca = 1'b0;
        deca = 1'b1;
        resw = 1'b0;
        plwc = 1'b0;
        enw = 1'b1;
        incw = 1'b1;
        decw = 1'b0;
        oedata = 1'b0;
      end
      
      6'b111_110: begin
        plar = 1'b0;
        plwr = 1'b0;
        sela = 1'bx;
        selw = 1'bx;
        plcr = 1'b0;
        seld = 2'bxx;
        plac = 1'b0;
        ena = 1'b1;
        inca = 1'b0;
        deca = 1'b1;
        resw = 1'b0;
        plwc = 1'b0;
        enw = 1'b0;
        incw = 1'b0;
        decw = 1'b0;
        oedata = 1'b0;
      end
    endcase
      
endmodule

AM2940/design.sv
// Chirica Andrei
// 1209A

`include"register.sv" 
`include"multiplexer.sv"
`include"counter.sv"
`include"donegen.sv"
`include"instructiondec.sv"


module AM2940(clk, I, datain, dataout, addrout, done, aci, aco, wci, wco);
  input clk, aci, wci;
  input [2:0] I;
  input [7:0] datain;
  output [7:0] addrout;
  output [7:0] dataout;
  output  wco, aco, done;
  
  
  // Variabile de transfer intre module
  wire plar, plwr, sela, selw, plcr, plac, ena, inca, deca, resw, plwc, enw, incw, decw, oedata;
  wire[1:0] seld;
  wire[7:0] arout, wrout, amout, wmout, acout, wcout;
  wire[2:0] crout;
  
  assign addrout = acout;
  
  // Decodorul de instructiuni. Face decode in functie de I(instruction) si CR(Command register)
  instruction_decoder instr_dec(.I(I), .CR(datain[2:0]), .plar(plar), .plwr(plwr), .sela(sela), .selw(selw), .plcr(plcr),
                      .seld(seld), .plac(plac), .ena(ena), .inca(inca), .deca(deca), .resw(resw),
                      .plwc(plwc), .enw(enw), .incw(incw), .decw(decw), .oedata(oedata));
 
  // Registrul de adresa
  reg8 addrReg(.clk(clk), .pl(plar), .din(datain[7:0]), .dout(arout[7:0])); 
  // Multiplexorul cu output in registrul numarator al adreselor
  mux_1_2 addrMux(.din0(datain[7:0]), .din1(arout[7:0]), .dout(amout[7:0]), .sel(sela));
  // Registrul numarator al adreselor
  counter_8b addrCnt(.clk(clk), .reset(1'b0), .pl(plac), .ci(aci), .cout(aco), .dec(deca), .inc(inca), .encnt(ena), .di(amout[7:0]), .dout(acout[7:0]));

  // Registrul pentru cuvinte
  reg8 wordReg(.clk(clk), .pl(plwr), .din(datain), .dout(wrout));
  // Multiplexor cu output in registrul numarator al cuvintelor
  mux_1_2 wordMux(.din0(datain), .din1(wrout), .dout(wmout[7:0]), .sel(selw));
  
  // Numaratorul de cuvinte
  counter_8b wordCnt(.clk(clk), .reset(resw), .pl(plwc), .ci(wci), .cout(wco), .dec(decw), .inc(incw), .encnt(enw), .di(wmout[7:0]), .dout(wcout[7:0]));
  
  // Registrul in care se stocheaza comanda
  reg3 controlReg(.clk(clk), .pl(plcr), .din(datain[2:0]), .dout(crout));
  
  // Multiplexor pentru a alege ce intra in magistrala de Data pentru output
  mux_1_3 dataMux(.din0(acout), .din1(wcout[7:0]), .din2(crout[2:0]), .dout(dataout), .sel(seld[1:0]));
  
  //Generatorul semnalul done care indica momentul cand s-a terminat executia
  //instructiunii
  done_gen done_generator(.dowc(wcout), .dowr(wrout), .doac(acout), .cinw(~wci), .mode(crout[1:0]), .done(done));
  

  
endmodule

AM2940/testbench.sv
module AM2940_tb();

  reg clkt, acit, wcit;
  reg [2:0] It;
  reg [7:0] dataint;
  wire[7:0] dataoutt, addroutt;
  wire wcot, acot, donet;
  
  AM2940 DUT(.clk(clkt), .I(It), .datain(dataint), .dataout(dataoutt), .addrout(addroutt), .done(donet), .aci(acit), .aco(acot), .wci(wcit), .wco(wcot));
 


  initial
    begin
      $dumpfile("dump.vcd");
      $dumpvars(0, DUT);
    end
  
	initial
    	begin
        	#0 clkt = 1'b1;
      	forever #5 clkt =~clkt;
    end
  

  initial
    #750 $finish;

  initial
    begin
      // Scrie in CR o valoare| cei 3 mai nesemnificativi biti din datain:
      // I: Write Control Register | CR: x 
      #5 It = 3'b0; acit = 1'b0; wcit = 1'b0; dataint = 8'b0010_0000;
      // Citeste valoarea stocata in CR 
      // t10 I: Read Control Register | CR: x
      #10 It = 3'b001;
      
      // t20 I: Load Counter register
      #10 It = 3'b110; dataint = 8'hac;
      
      
      //Testez incarcarile si citirile in registrul de adrese si numaratorul de adrese
      
      // t30 I: Load Address register
      #10 It = 3'b101;
      // t40 I: Read Address Counter
      #10 It = 3'b011;
      // t50 I: Write control register
      #10 It = 3'b0; dataint = 8'b0;
      // t60 I: Enable counters: AC++; Wc-- until 0
      #10 It = 3'b111;
      // t110 I: Reinitialize: AR -> AC
      #50 It = 3'b100;
      // t120 I: Read Address Register*
      #10 It = 3'b011;
      
      
      //Testez incarcarile si citirile in registrul de cuvinte si numaratorul de cuvinte
      // Caz 1: CR = 0,2,3 => D->WR, WC
      
      // t130 Load Word Count
      #10 It = 3'b110; dataint = 8'hcd;
      // t140 Read Word Count
      #10 It = 3'b010;
      // t150 Write Control Register
      #10 It = 3'b000; dataint = 8'b010;
      // t160 Enable counters
      #10 It = 3'b111;
      // t210 Reinitialize
      #50 It = 3'b100;
      // t220 Read WC;
      #10 It = 3'b010;
      
      //OBS: ***Numaratorul de cuvinte ia valoare 0 dupa instructiunea 6, chiar daca registrul de control nu are valoare 1. Valoarea lui dataout ramane cea din numaratorul de adrese.***
      
      // Caz 2: CR = 1 => D->WR, 0 -> WC
      
      
      // t230 Load Word Count
      #10 It = 3'b110; dataint = 8'h18;
      // t240 Read Word Count
      #10 It = 3'b010;
      // t250 Write Control Register
      #10 It = 3'b000; dataint = 8'b001;
      // t260 Enable counters
      #10 It = 3'b111;
      // t310 Reinitialize
      #50 It = 3'b100;
      // t320 Read WC;
      #10 It = 3'b010;
      
      
      
		//Enabling counters
      
      // t330 I: Load Address register
      #10 It = 3'b101; dataint = 8'hab;
      
      // t340 I: Load Word register
      #10 It = 3'b110; dataint = 8'h3;
      
      // t350 Write control register
      #10 It = 3'b000; dataint = 8'b0000_0000;
     
      
      
      
      // t360 I: Enable counters | CR: Inc ADDR , Dec Word
      #10 It = 3'b111;     
      
      // t410 I: Write control register
	  #50 It = 3'b000; dataint = 8'b0000_0001;
      
      // t420 I: Enable counters | CR: Inc ADDR , Inc Word
      #10 It = 3'b111;
      
      // t440 I: Write control register
	  #50 It = 3'b000; dataint = 8'b0000_0010;
      
      // t490 I: Enable counters | CR: Inc ADDR , Encw = 0;
      #10 It = 3'b111;
      
      // t500 I: Write control register
	  #50 It = 3'b000; dataint = 8'b0000_0100;
      
      // t550 I: Enable counters | CR: Dec ADDR , Dec Word
      #10 It = 3'b111;
      
      // t560 I: Write control register
	  #50 It = 3'b000; dataint = 8'b0000_0111;
      
      // t610 I: Enable counters | CR: Dec ADDR , Inc Word
      #10 It = 3'b111;
      
      // t620 I: Write control register
	  #50 It = 3'b000; dataint = 8'b0000_0110;
      
      // t670 I: Enable counters | CR: Dec ADDR , Enwc = 0
      #10 It = 3'b111;
      
      // t680 I: Read word counter
      #10 It = 3'b010;
      
      // t690 I: Read address counter
      #10 It = 3'b011;
      
      // t700 I: Read Control register
      #10 It = 3'b001;
         
 
    end

endmodule

AM2940/dump.vcd
$date
	Mon Sep 19 16:31:17 2022
$end
$version
	Icarus Verilog
$end
$timescale
	1s
$end
$scope module AM2940_tb $end
$scope module DUT $end
$var wire 3 ! I [2:0] $end
$var wire 1 " aci $end
$var wire 1 # aco $end
$var wire 8 $ acout [7:0] $end
$var wire 8 % addrout [7:0] $end
$var wire 8 & amout [7:0] $end
$var wire 8 ' arout [7:0] $end
$var wire 1 ( clk $end
$var wire 3 ) crout [2:0] $end
$var wire 8 * datain [7:0] $end
$var wire 8 + dataout [7:0] $end
$var wire 1 , deca $end
$var wire 1 - decw $end
$var wire 1 . done $end
$var wire 1 / ena $end
$var wire 1 0 enw $end
$var wire 1 1 inca $end
$var wire 1 2 incw $end
$var wire 1 3 oedata $end
$var wire 1 4 plac $end
$var wire 1 5 plar $end
$var wire 1 6 plcr $end
$var wire 1 7 plwc $end
$var wire 1 8 plwr $end
$var wire 1 9 resw $end
$var wire 1 : sela $end
$var wire 2 ; seld [1:0] $end
$var wire 1 < selw $end
$var wire 1 = wci $end
$var wire 1 > wco $end
$var wire 8 ? wcout [7:0] $end
$var wire 8 @ wmout [7:0] $end
$var wire 8 A wrout [7:0] $end
$scope module instr_dec $end
$var wire 3 B CR [2:0] $end
$var wire 3 C I [2:0] $end
$var reg 1 D deca $end
$var reg 1 E decw $end
$var reg 1 F ena $end
$var reg 1 G enw $end
$var reg 1 H inca $end
$var reg 1 I incw $end
$var reg 1 J oedata $end
$var reg 1 K plac $end
$var reg 1 L plar $end
$var reg 1 M plcr $end
$var reg 1 N plwc $end
$var reg 1 O plwr $end
$var reg 1 P resw $end
$var reg 1 Q sela $end
$var reg 2 R seld [1:0] $end
$var reg 1 S selw $end
$upscope $end
$scope module addrReg $end
$var wire 1 ( clk $end
$var wire 8 T din [7:0] $end
$var wire 1 5 pl $end
$var reg 8 U dout [7:0] $end
$upscope $end
$scope module addrMux $end
$var wire 8 V din0 [7:0] $end
$var wire 8 W din1 [7:0] $end
$var wire 8 X dout [7:0] $end
$var wire 1 : sel $end
$upscope $end
$scope module addrCnt $end
$var wire 1 " ci $end
$var wire 1 ( clk $end
$var wire 1 # cout $end
$var wire 1 , dec $end
$var wire 8 Y di [7:0] $end
$var wire 1 / encnt $end
$var wire 1 1 inc $end
$var wire 1 4 pl $end
$var wire 1 Z reset $end
$var reg 8 [ dout [7:0] $end
$upscope $end
$scope module wordReg $end
$var wire 1 ( clk $end
$var wire 8 \ din [7:0] $end
$var wire 1 8 pl $end
$var reg 8 ] dout [7:0] $end
$upscope $end
$scope module wordMux $end
$var wire 8 ^ din0 [7:0] $end
$var wire 8 _ din1 [7:0] $end
$var wire 8 ` dout [7:0] $end
$var wire 1 < sel $end
$upscope $end
$scope module wordCnt $end
$var wire 1 = ci $end
$var wire 1 ( clk $end
$var wire 1 > cout $end
$var wire 1 - dec $end
$var wire 8 a di [7:0] $end
$var wire 1 0 encnt $end
$var wire 1 2 inc $end
$var wire 1 7 pl $end
$var wire 1 9 reset $end
$var reg 8 b dout [7:0] $end
$upscope $end
$scope module controlReg $end
$var wire 1 ( clk $end
$var wire 3 c din [2:0] $end
$var wire 1 6 pl $end
$var reg 3 d dout [2:0] $end
$upscope $end
$scope module dataMux $end
$var wire 8 e din0 [7:0] $end
$var wire 8 f din1 [7:0] $end
$var wire 3 g din2 [2:0] $end
$var wire 2 h sel [1:0] $end
$var reg 8 i dout [7:0] $end
$upscope $end
$scope module done_generator $end
$var wire 1 j cinw $end
$var wire 8 k doac [7:0] $end
$var wire 8 l dowc [7:0] $end
$var wire 8 m dowr [7:0] $end
$var wire 2 n mode [1:0] $end
$var reg 1 o done $end
$upscope $end
$upscope $end
$upscope $end
$enddefinitions $end
#0
$dumpvars
0o
bx n
bx m
bx l
bx k
xj
bx i
bx h
bx g
bx f
bx e
bx d
bx c
bx b
bx a
bx `
bx _
bx ^
bx ]
bx \
bx [
0Z
bx Y
bx X
bx W
bx V
bx U
bx T
xS
bx R
xQ
0P
0O
0N
1M
0L
0K
0J
0I
0H
0G
0F
0E
0D
bx C
bx B
bx A
bx @
bx ?
0>
x=
x<
bx ;
x:
09
08
07
16
05
04
03
02
01
00
0/
0.
0-
0,
bx +
bx *
bx )
1(
bx '
bx &
bx %
bx $
0#
x"
bx !
$end
#5
xo
x.
b0 B
b0 c
1j
0(
b100000 *
b100000 T
b100000 V
b100000 \
b100000 ^
0=
0"
b0 !
b0 C
#10
b0 n
b0 d
b0 )
b0 g
1(
#15
b11111000 i
b11111000 +
1J
13
b1x R
b1x ;
b1x h
0M
06
0(
b1 !
b1 C
#20
1(
#25
bx i
bx +
b100 B
b100 c
b10101100 @
b10101100 `
b10101100 a
0J
03
1N
17
bx R
bx ;
bx h
0S
0<
1O
18
0(
b10101100 *
b10101100 T
b10101100 V
b10101100 \
b10101100 ^
b110 !
b110 C
#30
1o
1.
b10101100 b
b10101100 ?
b10101100 f
b10101100 l
b10101100 ]
b10101100 A
b10101100 _
b10101100 m
1(
#35
b10101100 &
b10101100 X
b10101100 Y
0N
07
1K
14
xS
x<
0Q
0:
0O
08
1L
15
0(
b101 !
b101 C
#40
b10101100 i
b10101100 +
b10101100 U
b10101100 '
b10101100 W
b10101100 [
b10101100 $
b10101100 e
b10101100 k
b10101100 %
1(
#45
1J
13
0K
04
b0 R
b0 ;
b0 h
xQ
x:
0L
05
0(
b11 !
b11 C
#50
1(
#55
b0 B
b0 c
bx0x0xx00 &
bx0x0xx00 X
bx0x0xx00 Y
bx0x0xx00 @
bx0x0xx00 `
bx0x0xx00 a
0J
03
bx R
bx ;
bx h
1M
16
0(
b0 *
b0 T
b0 V
b0 \
b0 ^
b0 !
b0 C
#60
1(
#65
1E
1-
1G
10
1H
11
1F
1/
0M
06
0(
b111 !
b111 C
#70
0o
0.
b10101101 i
b10101101 +
b10101011 b
b10101011 ?
b10101011 f
b10101011 l
b10101101 [
b10101101 $
b10101101 e
b10101101 k
b10101101 %
1(
#75
0(
#80
1o
1.
b10101110 i
b10101110 +
b10101110 [
b10101110 $
b10101110 e
b10101110 k
b10101110 %
b10101010 b
b10101010 ?
b10101010 f
b10101010 l
1(
#85
0(
#90
0o
0.
b10101111 i
b10101111 +
b10101001 b
b10101001 ?
b10101001 f
b10101001 l
b10101111 [
b10101111 $
b10101111 e
b10101111 k
b10101111 %
1(
#95
0(
#100
1o
1.
b10110000 i
b10110000 +
b10110000 [
b10110000 $
b10110000 e
b10110000 k
b10110000 %
b10101000 b
b10101000 ?
b10101000 f
b10101000 l
1(
#105
0(
#110
0o
0.
b10110001 i
b10110001 +
b10100111 b
b10100111 ?
b10100111 f
b10100111 l
b10110001 [
b10110001 $
b10110001 e
b10110001 k
b10110001 %
1(
#115
b10101100 @
b10101100 `
b10101100 a
b10101100 &
b10101100 X
b10101100 Y
0E
0-
0G
00
0H
01
0F
0/
1K
14
1S
1<
1Q
1:
0(
b100 !
b100 C
#120
b10101100 i
b10101100 +
b10101100 [
b10101100 $
b10101100 e
b10101100 k
b10101100 %
1(
#125
bx0x0xx00 @
bx0x0xx00 `
bx0x0xx00 a
bx0x0xx00 &
bx0x0xx00 X
bx0x0xx00 Y
1J
13
0K
04
b0 R
b0 ;
b0 h
xS
x<
xQ
x:
0(
b11 !
b11 C
#130
1(
#135
1P
19
b101 B
b101 c
b1xx0110x &
b1xx0110x X
b1xx0110x Y
b1xx0110x @
b1xx0110x `
b1xx0110x a
0J
03
0N
07
bx R
bx ;
bx h
xS
x<
1O
18
0(
b11001101 *
b11001101 T
b11001101 V
b11001101 \
b11001101 ^
b110 !
b110 C
#140
b11001101 @
b11001101 `
b11001101 a
1o
1.
b11001101 ]
b11001101 A
b11001101 _
b11001101 m
b0 b
b0 ?
b0 f
b0 l
1(
#145
b0 i
b0 +
1J
13
0P
09
b1 R
b1 ;
b1 h
0O
08
0(
b10 !
b10 C
#150
1(
#155
b10101100 i
b10101100 +
b10 B
b10 c
bx0x0xxx0 &
bx0x0xxx0 X
bx0x0xxx0 Y
bx00xxxx @
bx00xxxx `
bx00xxxx a
0J
03
bx R
bx ;
bx h
1M
16
0(
b10 *
b10 T
b10 V
b10 \
b10 ^
b0 !
b0 C
#160
0o
0.
b10 n
b10 d
b10 )
b10 g
1(
#165
1H
11
1F
1/
0M
06
0(
b111 !
b111 C
#170
b10101101 i
b10101101 +
b10101101 [
b10101101 $
b10101101 e
b10101101 k
b10101101 %
1(
#175
0(
#180
b10101110 i
b10101110 +
b10101110 [
b10101110 $
b10101110 e
b10101110 k
b10101110 %
1(
#185
0(
#190
b10101111 i
b10101111 +
b10101111 [
b10101111 $
b10101111 e
b10101111 k
b10101111 %
1(
#195
0(
#200
b10110000 i
b10110000 +
b10110000 [
b10110000 $
b10110000 e
b10110000 k
b10110000 %
1(
#205
0(
#210
b10110001 i
b10110001 +
b10110001 [
b10110001 $
b10110001 e
b10110001 k
b10110001 %
1(
#215
b11001101 @
b11001101 `
b11001101 a
b10101100 &
b10101100 X
b10101100 Y
0H
01
0F
0/
1K
14
1S
1<
1Q
1:
0(
b100 !
b100 C
#220
b10101100 i
b10101100 +
b10101100 [
b10101100 $
b10101100 e
b10101100 k
b10101100 %
1(
#225
b0 i
b0 +
bx00xxxx @
bx00xxxx `
bx00xxxx a
bx0x0xxx0 &
bx0x0xxx0 X
bx0x0xxx0 Y
1J
13
0K
04
b1 R
b1 ;
b1 h
xS
x<
xQ
x:
0(
b10 !
b10 C
#230
1(
#235
b10101100 i
b10101100 +
b0 B
b0 c
bx0xx1x00 &
bx0xx1x00 X
bx0xx1x00 Y
b11000 @
b11000 `
b11000 a
0J
03
1N
17
bx R
bx ;
bx h
0S
0<
1O
18
0(
b11000 *
b11000 T
b11000 V
b11000 \
b11000 ^
b110 !
b110 C
#240
b11000 ]
b11000 A
b11000 _
b11000 m
b11000 b
b11000 ?
b11000 f
b11000 l
1(
#245
b11000 i
b11000 +
1J
13
0N
07
b1 R
b1 ;
b1 h
xS
x<
0O
08
0(
b10 !
b10 C
#250
1(
#255
b10101100 i
b10101100 +
b1 B
b1 c
bx0x0xx0x &
bx0x0xx0x X
bx0x0xx0x Y
b0xx00x @
b0xx00x `
b0xx00x a
0J
03
bx R
bx ;
bx h
1M
16
0(
b1 *
b1 T
b1 V
b1 \
b1 ^
b0 !
b0 C
#260
1o
1.
b1 n
b1 d
b1 )
b1 g
1(
#265
1I
12
1G
10
1H
11
1F
1/
0M
06
0(
b111 !
b111 C
#270
0o
0.
b10101101 i
b10101101 +
b11001 b
b11001 ?
b11001 f
b11001 l
b10101101 [
b10101101 $
b10101101 e
b10101101 k
b10101101 %
1(
#275
0(
#280
b10101110 i
b10101110 +
b10101110 [
b10101110 $
b10101110 e
b10101110 k
b10101110 %
b11010 b
b11010 ?
b11010 f
b11010 l
1(
#285
0(
#290
b10101111 i
b10101111 +
b11011 b
b11011 ?
b11011 f
b11011 l
b10101111 [
b10101111 $
b10101111 e
b10101111 k
b10101111 %
1(
#295
0(
#300
b10110000 i
b10110000 +
b10110000 [
b10110000 $
b10110000 e
b10110000 k
b10110000 %
b11100 b
b11100 ?
b11100 f
b11100 l
1(
#305
0(
#310
b10110001 i
b10110001 +
b11101 b
b11101 ?
b11101 f
b11101 l
b10110001 [
b10110001 $
b10110001 e
b10110001 k
b10110001 %
1(
#315
b10101100 &
b10101100 X
b10101100 Y
0I
02
0G
00
1P
19
0H
01
0F
0/
1K
14
1Q
1:
0(
b100 !
b100 C
#320
b10101100 i
b10101100 +
b10101100 [
b10101100 $
b10101100 e
b10101100 k
b10101100 %
b0 b
b0 ?
b0 f
b0 l
1(
#325
b0 i
b0 +
bx0x0xx0x &
bx0x0xx0x X
bx0x0xx0x Y
1J
13
0P
09
0K
04
b1 R
b1 ;
b1 h
xQ
x:
0(
b10 !
b10 C
#330
1(
#335
b10101100 i
b10101100 +
b11 B
b11 c
b10101011 &
b10101011 X
b10101011 Y
bx0xx10xx @
bx0xx10xx `
bx0xx10xx a
0J
03
1K
14
bx R
bx ;
bx h
0Q
0:
1L
15
0(
b10101011 *
b10101011 T
b10101011 V
b10101011 \
b10101011 ^
b101 !
b101 C
#340
b10101011 i
b10101011 +
b10101011 U
b10101011 '
b10101011 W
b10101011 [
b10101011 $
b10101011 e
b10101011 k
b10101011 %
1(
#345
bx0x0x011 &
bx0x0x011 X
bx0x0x011 Y
b11 @
b11 `
b11 a
1N
17
0K
04
0S
0<
xQ
x:
1O
18
0L
05
0(
b11 *
b11 T
b11 V
b11 \
b11 ^
b110 !
b110 C
#350
1o
1.
b11 b
b11 ?
b11 f
b11 l
b11 ]
b11 A
b11 _
b11 m
1(
#355
b0 B
b0 c
bx0x0x0xx &
bx0x0x0xx X
bx0x0x0xx Y
b0xx @
b0xx `
b0xx a
0N
07
1M
16
xS
x<
0O
08
0(
b0 *
b0 T
b0 V
b0 \
b0 ^
b0 !
b0 C
#360
0o
0.
b0 n
b0 d
b0 )
b0 g
1(
#365
1E
1-
1G
10
1H
11
1F
1/
0M
06
0(
b111 !
b111 C
#370
1o
1.
b10101100 i
b10101100 +
b10 b
b10 ?
b10 f
b10 l
b10101100 [
b10101100 $
b10101100 e
b10101100 k
b10101100 %
1(
#375
0(
#380
0o
0.
b10101101 i
b10101101 +
b10101101 [
b10101101 $
b10101101 e
b10101101 k
b10101101 %
b1 b
b1 ?
b1 f
b1 l
1(
#385
0(
#390
1>
1o
1.
b10101110 i
b10101110 +
b0 b
b0 ?
b0 f
b0 l
b10101110 [
b10101110 $
b10101110 e
b10101110 k
b10101110 %
1(
#395
0(
#400
0>
0o
0.
b10101111 i
b10101111 +
b10101111 [
b10101111 $
b10101111 e
b10101111 k
b10101111 %
b11111111 b
b11111111 ?
b11111111 f
b11111111 l
1(
#405
0(
#410
1o
1.
b10110000 i
b10110000 +
b11111110 b
b11111110 ?
b11111110 f
b11111110 l
b10110000 [
b10110000 $
b10110000 e
b10110000 k
b10110000 %
1(
#415
b1 B
b1 c
bx0x0x0x1 &
bx0x0x0x1 X
bx0x0x0x1 Y
b0x1 @
b0x1 `
b0x1 a
0E
0-
0G
00
0H
01
0F
0/
1M
16
0(
b1 *
b1 T
b1 V
b1 \
b1 ^
b0 !
b0 C
#420
0o
0.
b1 n
b1 d
b1 )
b1 g
1(
#425
1I
12
1G
10
1H
11
1F
1/
0M
06
0(
b111 !
b111 C
#430
1>
b10110001 i
b10110001 +
b11111111 b
b11111111 ?
b11111111 f
b11111111 l
b10110001 [
b10110001 $
b10110001 e
b10110001 k
b10110001 %
1(
#435
0(
#440
0>
b10110010 i
b10110010 +
b10110010 [
b10110010 $
b10110010 e
b10110010 k
b10110010 %
b0 b
b0 ?
b0 f
b0 l
1(
#445
0(
#450
b10110011 i
b10110011 +
b1 b
b1 ?
b1 f
b1 l
b10110011 [
b10110011 $
b10110011 e
b10110011 k
b10110011 %
1(
#455
0(
